asyncio_inspector/__init__.py
asyncio_inspector/events.py
asyncio_inspector/patcher.py
asyncio_inspector/reporter.py
asyncio_inspector/stats.py
asyncio_inspector-0.1.0.dist-info/LICENSE
asyncio_inspector-0.1.0.dist-info/METADATA
asyncio_inspector-0.1.0.dist-info/WHEEL
asyncio_inspector-0.1.0.dist-info/entry_points.txt
asyncio_inspector-0.1.0.dist-info/top_level.txt
asyncio_inspector-0.1.0.dist-info/RECORD
