Metadata-Version: 2.1
Name: asyncio-inspector
Version: 0.1.0
Summary: Awesome asyncio_inspector created by pappacena
Home-page: https://github.com/pappacena/asyncio-inspector/
Author: pappacena
License-File: LICENSE
Requires-Dist: sortedcollections
Provides-Extra: test
Requires-Dist: pytest ; extra == 'test'
Requires-Dist: coverage ; extra == 'test'
Requires-Dist: flake8 ; extra == 'test'
Requires-Dist: black ; extra == 'test'
Requires-Dist: isort ; extra == 'test'
Requires-Dist: pytest-cov ; extra == 'test'
Requires-Dist: codecov ; extra == 'test'
Requires-Dist: mypy ; extra == 'test'
Requires-Dist: gitchangelog ; extra == 'test'
Requires-Dist: mkdocs ; extra == 'test'
